mydog/__init__.py
mydog/mydog.py
mydog-1.0.4.dist-info/METADATA
mydog-1.0.4.dist-info/WHEEL
mydog-1.0.4.dist-info/entry_points.txt
mydog-1.0.4.dist-info/top_level.txt
mydog-1.0.4.dist-info/RECORD
