Metadata-Version: 2.1
Name: mydog
Version: 1.0.4
Summary: prints the contents of the file
Home-page: https://github.com/Brijeshkrishna/mydog
Author: Brijesh krishna
Author-email: brijesh.krishna@gmail.com
License: MIT
Keywords: mydog,cat,dog,console print,python print,python,colour print
Platform: UNKNOWN
Classifier: Intended Audience :: Developers
Classifier: Programming Language :: Python :: 3
Classifier: Operating System :: Unix
Classifier: Operating System :: MacOS :: MacOS X
Classifier: Operating System :: Microsoft :: Windows
Requires-Dist: click
Requires-Dist: termcolor
